zippyshare_downloader/__init__.py
zippyshare_downloader/__main__.py
zippyshare_downloader/downloader.py
zippyshare_downloader/errors.py
zippyshare_downloader/fetcher.py
zippyshare_downloader/file.py
zippyshare_downloader/network.py
zippyshare_downloader/parser.py
zippyshare_downloader/patterns.py
zippyshare_downloader/utils.py
zippyshare_downloader/cli/__init__.py
zippyshare_downloader/cli/process.py
zippyshare_downloader/cli/utils.py
zippyshare_downloader-0.3.4.dist-info/LICENSE
zippyshare_downloader-0.3.4.dist-info/METADATA
zippyshare_downloader-0.3.4.dist-info/WHEEL
zippyshare_downloader-0.3.4.dist-info/entry_points.txt
zippyshare_downloader-0.3.4.dist-info/top_level.txt
zippyshare_downloader-0.3.4.dist-info/RECORD
