Metadata-Version: 2.1
Name: zippyshare-downloader
Version: 0.3.4
Summary: Download file from zippyshare directly with python
Home-page: https://github.com/trollfist20/zippyshare-downloader
Download-URL: https://github.com/trollfist20/zippyshare-downloader/archive/0.3.4.tar.gz
Author: Rahman Yusuf
Author-email: danipart4@gmail.com
License: MIT
Keywords: zippyshare,zippyshare-download
Classifier: Development Status :: 5 - Production/Stable
Classifier: Intended Audience :: Developers
Classifier: License :: OSI Approved :: MIT License
Classifier: Programming Language :: Python :: 3
Classifier: Programming Language :: Python :: 3.5
Classifier: Programming Language :: Python :: 3.6
Classifier: Programming Language :: Python :: 3.7
Classifier: Programming Language :: Python :: 3.8
Classifier: Programming Language :: Python :: 3.9
Classifier: Programming Language :: Python :: 3.10
Requires-Python: >=3.5
License-File: LICENSE
Requires-Dist: bs4
Requires-Dist: requests[socks]
Requires-Dist: tqdm
Requires-Dist: aiohttp
Provides-Extra: docs
Requires-Dist: sphinx ; extra == 'docs'
Requires-Dist: furo ; extra == 'docs'
Provides-Extra: speed
Requires-Dist: uvloop ; extra == 'speed'
Requires-Dist: lxml ; extra == 'speed'
